Metadata-Version: 2.1
Name: pylcount
Version: 0.1.1
Summary: Python file line counter.
Home-page: https://github.com/jaedsonpys/pylcount
Author: Jaedson Silva
Author-email: imunknowuser@protonmail.com
License: MIT
Keywords: line,counter,count,file
Platform: any
License-File: LICENSE
